odoo/addons/ssi_sequence_mixin/README.rst
odoo/addons/ssi_sequence_mixin/__init__.py
odoo/addons/ssi_sequence_mixin/__manifest__.py
odoo/addons/ssi_sequence_mixin/menu.xml
odoo/addons/ssi_sequence_mixin/i18n/ssi_sequence_mixin.pot
odoo/addons/ssi_sequence_mixin/models/__init__.py
odoo/addons/ssi_sequence_mixin/models/mixin_sequence.py
odoo/addons/ssi_sequence_mixin/models/sequence_template.py
odoo/addons/ssi_sequence_mixin/security/ir.model.access.csv
odoo/addons/ssi_sequence_mixin/static/description/icon.png
odoo/addons/ssi_sequence_mixin/views/sequence_template_views.xml
odoo14_addon_ssi_sequence_mixin-14.0.2.0.2.dist-info/METADATA
odoo14_addon_ssi_sequence_mixin-14.0.2.0.2.dist-info/WHEEL
odoo14_addon_ssi_sequence_mixin-14.0.2.0.2.dist-info/top_level.txt
odoo14_addon_ssi_sequence_mixin-14.0.2.0.2.dist-info/RECORD
